fairmd/__init__.py
fairmd/lipids/__init__.py
fairmd/lipids/_version.py
fairmd/lipids/analyze.py
fairmd/lipids/analyze_nmrpca.py
fairmd/lipids/core.py
fairmd/lipids/databankLibrary.py
fairmd/lipids/databankio.py
fairmd/lipids/databankop.py
fairmd/lipids/jpyroutines.py
fairmd/lipids/jsonEncoders.py
fairmd/lipids/maicos.py
fairmd/lipids/openmm_parser.py
fairmd/lipids/plottings.py
fairmd/lipids/quality.py
fairmd/lipids/utils.py
fairmd/lipids/SchemaValidation/ValidateYAML.py
fairmd/lipids/SchemaValidation/__init__.py
fairmd/lipids/SchemaValidation/Schema/info_template.yaml
fairmd/lipids/SchemaValidation/Schema/info_yml_schema.json
fairmd/lipids/bin/__init__.py
fairmd/lipids/bin/add_simulation.py
fairmd/lipids/bin/compute_databank.py
fairmd/lipids/bin/evaluate_quality.py
fairmd/lipids/bin/initialize_data.py
fairmd/lipids/bin/make_ranking.py
fairmd/lipids/bin/match_experiments.py
fairmd/lipids/data/ToyData/.gitignore
fairmd/lipids/data/ToyData/Molecules/membrane/CHOL/mappingCHOLESTEROLlipid14.yaml
fairmd/lipids/data/ToyData/Molecules/membrane/CHOL/metadata.yaml
fairmd/lipids/data/ToyData/Molecules/membrane/DPPC/mappingDPPCberger.yaml
fairmd/lipids/data/ToyData/Molecules/membrane/DPPC/metadata.yaml
fairmd/lipids/data/ToyData/Molecules/membrane/POPC/mappingPOPCcharmm.yaml
fairmd/lipids/data/ToyData/Molecules/membrane/POPC/mappingPOPClipid14.yaml
fairmd/lipids/data/ToyData/Molecules/membrane/POPC/metadata.yaml
fairmd/lipids/data/ToyData/Molecules/membrane/POPE/mappingPOPEGROMOS43A1-S3.yaml
fairmd/lipids/data/ToyData/Molecules/membrane/POPE/mappingPOPEcharmm.yaml
fairmd/lipids/data/ToyData/Molecules/membrane/POPE/metadata.yaml
fairmd/lipids/data/ToyData/Molecules/membrane/TOCL/mappingTOCLcharmm.yaml
fairmd/lipids/data/ToyData/Molecules/membrane/TOCL/metadata.yaml
fairmd/lipids/data/ToyData/Molecules/solution/CLA/mappingCL.yaml
fairmd/lipids/data/ToyData/Molecules/solution/SOD/mappingNA.yaml
fairmd/lipids/data/ToyData/Molecules/solution/SOD/mappingSOD.yaml
fairmd_lipids-1.3.2a0.dist-info/licenses/AUTHORS.md
fairmd_lipids-1.3.2a0.dist-info/licenses/LICENSE
fairmd_lipids-1.3.2a0.dist-info/METADATA
fairmd_lipids-1.3.2a0.dist-info/WHEEL
fairmd_lipids-1.3.2a0.dist-info/entry_points.txt
fairmd_lipids-1.3.2a0.dist-info/top_level.txt
fairmd_lipids-1.3.2a0.dist-info/RECORD
