Metadata-Version: 2.4
Name: fairmd-lipids
Version: 1.3.2a0
Summary: FAIRMD Lipids project (formerly NMRlipids) contains the core functionality for managing and accessing the Database.
Author-email: NMRlipids Open Collaboration <databank@nmrlipids.fi>
License-Expression: GPL-3.0-or-later
Project-URL: homepage, https://FAIRMD_lipids.nmrlipids.fi
Project-URL: documentation, https://nmrlipids.github.io/FAIRMD_lipids/latest/
Project-URL: repository, https://github.com/NMRLipids/FAIRMD_lipids
Project-URL: issues, https://github.com/NMRLipids/FAIRMD_lipids/issues
Keywords: Science,Molecular Dynamics,Membranes
Classifier: Development Status :: 4 - Beta
Classifier: Environment :: Console
Classifier: Intended Audience :: Science/Research
Classifier: Operating System :: OS Independent
Classifier: Programming Language :: Python
Classifier: Programming Language :: Python :: 3
Classifier: Topic :: Scientific/Engineering
Classifier: Topic :: Scientific/Engineering :: Bio-Informatics
Classifier: Topic :: Scientific/Engineering :: Chemistry
Classifier: Topic :: Software Development :: Libraries :: Python Modules
Classifier: Topic :: System :: Shells
License-File: LICENSE
License-File: AUTHORS.md
Requires-Dist: buildh>=1.6.1
Requires-Dist: MDAnalysis<2.10,>=2.7.0
Requires-Dist: maicos<0.12,>=0.11.2
Requires-Dist: numpy>=2.0
Requires-Dist: pandas>=2.0.0
Requires-Dist: PyYAML>=6.0.0
Requires-Dist: tqdm>=4.5.0
Requires-Dist: periodictable>=1.5.0
Requires-Dist: Deprecated
Requires-Dist: scipy
Requires-Dist: jsonschema
Dynamic: license-file
